base16_shell_preview/__init__.py
base16_shell_preview/__main__.py
base16_shell_preview-1.0.0.dist-info/LICENSE
base16_shell_preview-1.0.0.dist-info/METADATA
base16_shell_preview-1.0.0.dist-info/WHEEL
base16_shell_preview-1.0.0.dist-info/entry_points.txt
base16_shell_preview-1.0.0.dist-info/top_level.txt
base16_shell_preview-1.0.0.dist-info/RECORD
