Metadata-Version: 2.1
Name: base16-shell-preview
Version: 1.0.0
Summary: Browse and preview Base16 Shell themes in your terminal.
Home-page: https://github.com/nvllsvm/base16-shell-preview
Author: Andrew Rabert
Author-email: ar@nullsum.net
License: MIT
Platform: UNKNOWN
Classifier: Development Status :: 4 - Beta
Classifier: Intended Audience :: End Users/Desktop
Classifier: License :: OSI Approved :: MIT License
Classifier: Programming Language :: Python :: 3
Requires-Python: >=3.6
